chatfaq_cli/__init__.py
chatfaq_cli/__main__.py
chatfaq_cli/chatfaq
chatfaq_cli/config/__init__.py
chatfaq_cli/conversations/__init__.py
chatfaq_cli/data/__init__.py
chatfaq_cli/data/auto_generated_titles.py
chatfaq_cli/data/knowledge_bases.py
chatfaq_cli/data/knowledge_items.py
chatfaq_cli/data/utils.py
chatfaq_cli/helpers/__init__.py
chatfaq_cli/rag_pipeline/__init__.py
chatfaq_cli/rag_pipeline/generation_config.py
chatfaq_cli/rag_pipeline/llm_config.py
chatfaq_cli/rag_pipeline/prompt_config.py
chatfaq_cli/rag_pipeline/rag_config.py
chatfaq_cli/rag_pipeline/retriever_config.py
chatfaq_cli/reviews/__init__.py
chatfaq_cli/senders/__init__.py
chatfaq_cli-0.1.9.dist-info/METADATA
chatfaq_cli-0.1.9.dist-info/WHEEL
chatfaq_cli-0.1.9.dist-info/entry_points.txt
chatfaq_cli-0.1.9.dist-info/RECORD
