Metadata-Version: 2.1
Name: chatfaq_cli
Version: 0.1.9
Summary: 
Author: Hector Soria
Author-email: hector.soria@with-madrid.com
Requires-Python: >=3,<4
Classifier: Programming Language :: Python :: 3
Classifier: Programming Language :: Python :: 3.4
Classifier: Programming Language :: Python :: 3.5
Classifier: Programming Language :: Python :: 3.6
Classifier: Programming Language :: Python :: 3.7
Classifier: Programming Language :: Python :: 3.8
Classifier: Programming Language :: Python :: 3.9
Classifier: Programming Language :: Python :: 3.10
Classifier: Programming Language :: Python :: 3.11
Requires-Dist: crochet (>=2.1.1,<3.0.0)
Requires-Dist: fire (>=0.5.0,<0.6.0)
Requires-Dist: requests (>=2.30.0,<3.0.0)
Requires-Dist: tqdm (>=4.65.0,<5.0.0)
Requires-Dist: typer[all] (>=0.9.0,<0.10.0)
